vesicashapi/__init__.py
vesicashapi/auth.py
vesicashapi/base.py
vesicashapi/vesicash.py
vesicashapi-1.0.0.dist-info/LICENSE
vesicashapi-1.0.0.dist-info/METADATA
vesicashapi-1.0.0.dist-info/WHEEL
vesicashapi-1.0.0.dist-info/top_level.txt
vesicashapi-1.0.0.dist-info/RECORD
