Metadata-Version: 2.1
Name: vesicashapi
Version: 1.0.0
Summary: A python library to consume Vesicash API
Home-page: https://github.com/vesicash/vesicash-python
Author: Precious Opusunju
Author-email: precious@vesicash.com
License: MIT
Keywords: vesicash python library
Platform: UNKNOWN
Classifier: Development Status :: 4 - Beta
Classifier: Intended Audience :: Developers
Classifier: License :: OSI Approved :: MIT License
Classifier: Programming Language :: Python :: 3
Classifier: Programming Language :: Python :: 3.6
Requires-Dist: requests
Provides-Extra: test
Requires-Dist: coverage ; extra == 'test'
